symparsepy-0.1.1.dist-info/METADATA
symparsepy-0.1.1.dist-info/WHEEL
symparsepy-0.1.1.dist-info/licenses/LICENSE
symparsepy/__init__.py
symparsepy/symparsepy.cpython-312-x86_64-linux-gnu.so
symparsepy-0.1.1.dist-info/RECORD
