Metadata-Version: 2.3
Name: symparsepy
Version: 0.1.1
License-File: LICENSE
Summary: symparsepy is a Rust-based Python package for parsing symbols from PDB files. This package leverages the pyo3 library to create Python bindings for Rust code.
License: MIT License
Requires-Python: >=3.12
Project-URL: Repository, https://github.com/P1tt1cus/SymparsePy
